nova/__init__.py
nova/mvvm/__init__.py
nova/mvvm/bindings_map.py
nova/mvvm/interface.py
nova/mvvm/pydantic_utils.py
nova/mvvm/_internal/pydantic_utils.py
nova/mvvm/_internal/pyqt_communicator.py
nova/mvvm/_internal/utils.py
nova/mvvm/panel_binding/__init__.py
nova/mvvm/panel_binding/binding.py
nova/mvvm/pyqt5_binding/__init__.py
nova/mvvm/pyqt5_binding/binding.py
nova/mvvm/pyqt5_binding/pyqt5_worker.py
nova/mvvm/pyqt6_binding/__init__.py
nova/mvvm/pyqt6_binding/binding.py
nova/mvvm/pyqt6_binding/pyqt6_worker.py
nova/mvvm/trame_binding/__init__.py
nova/mvvm/trame_binding/binding.py
nova/mvvm/trame_binding/trame_worker.py
nova_mvvm-0.13.1.dist-info/METADATA
nova_mvvm-0.13.1.dist-info/WHEEL
nova_mvvm-0.13.1.dist-info/licenses/LICENSE
nova_mvvm-0.13.1.dist-info/RECORD
