Metadata-Version: 2.4
Name: nova-mvvm
Version: 0.13.1
Summary: A Python Package for Model-View-ViewModel pattern
Author-email: "Yakubov, Sergey" <yakubovs@ornl.gov>
License-Expression: MIT
License-File: LICENSE
Keywords: MVVM,python
Requires-Python: <3.14,>=3.10
Requires-Dist: deepdiff
Requires-Dist: pydantic
Requires-Dist: trame
Provides-Extra: panel
Requires-Dist: panel; extra == 'panel'
Provides-Extra: pyqt5
Requires-Dist: pyqt5; extra == 'pyqt5'
Provides-Extra: pyqt6
Requires-Dist: pyqt6; extra == 'pyqt6'
